bencode/__init__.py
bencode/decode.py
bencode/encode.py
bencode_vug-0.1.0.dist-info/LICENSE
bencode_vug-0.1.0.dist-info/METADATA
bencode_vug-0.1.0.dist-info/WHEEL
bencode_vug-0.1.0.dist-info/top_level.txt
bencode_vug-0.1.0.dist-info/RECORD
