Metadata-Version: 2.1
Name: bencode-vug
Version: 0.1.0
Summary: A package to encode and decode bencoded data
Author-email: Goncalo Azevedo <goncalooazevedo@outlook.com>
License: GNU GENERAL PUBLIC LICENSE
Project-URL: Homepage, https://github.com/vugonz/bencode
Project-URL: Bug Tracker, https://github.com/vugonz/bencode/issues
Project-URL: Source, https://github.com/vugonz/bencode/
Classifier: Programming Language :: Python :: 3
Classifier: Operating System :: OS Independent
Requires-Python: >=3.7
License-File: LICENSE
